b3dmath/__init__.py
b3dmath/algebra.py
b3dmath/arithmetic.py
b3dmath/primes.py
b3dmath/sequences.py
b3dmath/geometry/__init__.py
b3dmath/geometry/angles.py
b3dmath/geometry/coords.py
b3dmath/geometry/line.py
b3dmath/geometry/transform.py
b3dmath/geometry/tri.py
b3dmath/geometry/shapes/__init__.py
b3dmath/geometry/shapes/cone.py
b3dmath/geometry/shapes/cuboid.py
b3dmath/geometry/shapes/plane.py
b3dmath/geometry/shapes/sphere.py
b3dmath-0.2.0.dist-info/licenses/LICENSE
b3dmath-0.2.0.dist-info/METADATA
b3dmath-0.2.0.dist-info/WHEEL
b3dmath-0.2.0.dist-info/top_level.txt
b3dmath-0.2.0.dist-info/RECORD
