Metadata-Version: 2.4
Name: b3dmath
Version: 0.2.0
Summary: Utility 3D Math and Geometry library for Python.
Home-page: https://github.com/bailey3d/b3dmath
Author: Your Name
Author-email: bailey@bailey3d.com
License: MIT
Classifier: Programming Language :: Python :: 3
Classifier: License :: OSI Approved :: MIT License
Classifier: Operating System :: OS Independent
Requires-Python: >=3.7
License-File: LICENSE
Requires-Dist: numpy
Requires-Dist: scipy
Dynamic: author
Dynamic: author-email
Dynamic: classifier
Dynamic: home-page
Dynamic: license
Dynamic: license-file
Dynamic: requires-dist
Dynamic: requires-python
Dynamic: summary
